{
  "blog": [
    {
      "title": "Where does it come from...testing",
      "des": "Contrary to popular belief,.Testing testing testing",
      "img": "http://eutd.eu/wp-content/uploads/2017/03/healthcare-technology-8-04-2015-1024x652.jpg",
      "date": "5/13/2020",
      "id": "2R"
    },
    {
      "id": "7R",
      "title": "Where does it come from",
      "des": "Contrary to popular belief.",
      "date": "20-6-2040",
      "img": "http://eutd.eu/wp-content/uploads/2017/03/healthcare-technology-8-04-2015-1024x652.jpg"
    },
    {
      "id": "7K",
      "title": "Where does it come from",
      "des": "Contrary to popular belief.",
      "date": "20-6-2040",
      "img": "http://eutd.eu/wp-content/uploads/2017/03/healthcare-technology-8-04-2015-1024x652.jpg"
    },
    {
      "id": "5R",
      "title": "Where does it come from",
      "des": "Contrary to popular belief.",
      "date": "20-6-2040",
      "img": "http://eutd.eu/wp-content/uploads/2017/03/healthcare-technology-8-04-2015-1024x652.jpg"
    }
  ],
  "event": [
    {
      "title": "Where does it come from...testing",
      "des": "Contrary to popular belief, Lorem Ipsum .Testing, ",
      "time": "San Francisco, CA, USA",
      "img": "https://giveuselife.org/wp-content/uploads/2017/03/636219062613811054-2023111419_technology-5-820x500.jpg",
      "date": "5/13/2020",
      "id": "2H"
    },
    {
      "title": "covid19",
      "des": "njndneiieiwinnjv tllvl;lvmx jjrvv ",
      "time": "San Francisco, CA, USA",
      "img": "https://techupdatess.com/wp-content/uploads/2019/10/1571036750_960x0-850x491.jpg",
      "date": "5/5/2020",
      "id": "T_RHL7K"
    },
    {
      "title": "covid19",
      "des": "njndneiieiwinnjv tllvl;lvmx jjrvv ",
      "time": "San Francisco, CA, USA",
      "img": "https://techupdatess.com/wp-content/uploads/2019/10/1571036750_960x0-850x491.jpg",
      "date": "5/5/2020",
      "id": "T_RHL7K"
    },
    {
      "title": "covid19",
      "des": "njndneiieiwinnjv tllvl;lvmx jjrvv ",
      "time": "San Francisco, CA, USA",
      "img": "https://techupdatess.com/wp-content/uploads/2019/10/1571036750_960x0-850x491.jpg",
      "date": "5/5/2020",
      "id": "T_RHL7K"
    }
  ]
}
